<?xml version="1.0" encoding="utf-8"?><ArrayOfString xmlns:xsi="http://www.w3.org/2001/XMLSchema-instance" xmlns:xsd="http://www.w3.org/2001/XMLSchema"><string>D:\Pachore_Mayuresh_ASDP\Pachore_Mayuresh_Project_2\Pachore_Mayuresh_Project_2\Temp\Objects\Config1\X20CP1382\.mappView\Type_Sass._markerfile</string><string>D:\Pachore_Mayuresh_ASDP\Pachore_Mayuresh_Project_2\Pachore_Mayuresh_Project_2\Temp\Objects\Config1\X20CP1382\.mappView/data/wwwRoot/BRVisu/css/types\Area_default.scss.css</string><string>D:\Pachore_Mayuresh_ASDP\Pachore_Mayuresh_Project_2\Pachore_Mayuresh_Project_2\Temp\Objects\Config1\X20CP1382\.mappView/data/wwwRoot/BRVisu/css/types\Body_default.scss.css</string><string>D:\Pachore_Mayuresh_ASDP\Pachore_Mayuresh_Project_2\Pachore_Mayuresh_Project_2\Temp\Objects\Config1\X20CP1382\.mappView/data/wwwRoot/BRVisu/css/types\ChangePasswordDialog_default.scss.css</string><string>D:\Pachore_Mayuresh_ASDP\Pachore_Mayuresh_Project_2\Pachore_Mayuresh_Project_2\Temp\Objects\Config1\X20CP1382\.mappView/data/wwwRoot/BRVisu/css/types\Dialog_default.scss.css</string><string>D:\Pachore_Mayuresh_ASDP\Pachore_Mayuresh_Project_2\Pachore_Mayuresh_Project_2\Temp\Objects\Config1\X20CP1382\.mappView/data/wwwRoot/BRVisu/css/types\ElementFocus_default.scss.css</string><string>D:\Pachore_Mayuresh_ASDP\Pachore_Mayuresh_Project_2\Pachore_Mayuresh_Project_2\Temp\Objects\Config1\X20CP1382\.mappView/data/wwwRoot/BRVisu/css/types\Focus_default.scss.css</string><string>D:\Pachore_Mayuresh_ASDP\Pachore_Mayuresh_Project_2\Pachore_Mayuresh_Project_2\Temp\Objects\Config1\X20CP1382\.mappView/data/wwwRoot/BRVisu/css/types\MessageBox_default.scss.css</string><string>D:\Pachore_Mayuresh_ASDP\Pachore_Mayuresh_Project_2\Pachore_Mayuresh_Project_2\Temp\Objects\Config1\X20CP1382\.mappView/data/wwwRoot/BRVisu/css/types\ModalDimmer_default.scss.css</string><string>D:\Pachore_Mayuresh_ASDP\Pachore_Mayuresh_Project_2\Pachore_Mayuresh_Project_2\Temp\Objects\Config1\X20CP1382\.mappView/data/wwwRoot/BRVisu/css/types\Page_default.scss.css</string><string>D:\Pachore_Mayuresh_ASDP\Pachore_Mayuresh_Project_2\Pachore_Mayuresh_Project_2\Temp\Objects\Config1\X20CP1382\.mappView/data/wwwRoot/BRVisu/css/types\Scrollbar_default.scss.css</string><string>D:\Pachore_Mayuresh_ASDP\Pachore_Mayuresh_Project_2\Pachore_Mayuresh_Project_2\Temp\Objects\Config1\X20CP1382\.mappView/data/wwwRoot/BRVisu/css/types\Selection_default.scss.css</string><string>D:\Pachore_Mayuresh_ASDP\Pachore_Mayuresh_Project_2\Pachore_Mayuresh_Project_2\Temp\Objects\Config1\X20CP1382\.mappView/data/wwwRoot/BRVisu/css/types\StartupProgressBar_default.scss.css</string><string>D:\Pachore_Mayuresh_ASDP\Pachore_Mayuresh_Project_2\Pachore_Mayuresh_Project_2\Temp\Objects\Config1\X20CP1382\.mappView/data/wwwRoot/BRVisu/css/types\TableConfigurationDialog_default.scss.css</string><string>D:\Pachore_Mayuresh_ASDP\Pachore_Mayuresh_Project_2\Pachore_Mayuresh_Project_2\Temp\Objects\Config1\X20CP1382\.mappView/data/wwwRoot/BRVisu/css/types\Tooltip_default.scss.css</string><string>D:\Pachore_Mayuresh_ASDP\Pachore_Mayuresh_Project_2\Pachore_Mayuresh_Project_2\Temp\Objects\Config1\X20CP1382\.mappView/data/wwwRoot/BRVisu\Media/Down_Pointer.png</string><string>D:\Pachore_Mayuresh_ASDP\Pachore_Mayuresh_Project_2\Pachore_Mayuresh_Project_2\Temp\Objects\Config1\X20CP1382\.mappView/data/wwwRoot/BRVisu\Media/Left_Pointer.png</string><string>D:\Pachore_Mayuresh_ASDP\Pachore_Mayuresh_Project_2\Pachore_Mayuresh_Project_2\Temp\Objects\Config1\X20CP1382\.mappView/data/wwwRoot/BRVisu\Media/Right_Pointer.png</string><string>D:\Pachore_Mayuresh_ASDP\Pachore_Mayuresh_Project_2\Pachore_Mayuresh_Project_2\Temp\Objects\Config1\X20CP1382\.mappView/data/wwwRoot/BRVisu\Media/Up_Pointer.png</string><string>D:\Pachore_Mayuresh_ASDP\Pachore_Mayuresh_Project_2\Pachore_Mayuresh_Project_2\Temp\Objects\Config1\X20CP1382\IAT_MEDIA.job</string><string>D:\Pachore_Mayuresh_ASDP\Pachore_Mayuresh_Project_2\Pachore_Mayuresh_Project_2\Temp\Objects\Config1\X20CP1382\.mappView/data/wwwRoot\Control_Panel.json</string><string>D:\Pachore_Mayuresh_ASDP\Pachore_Mayuresh_Project_2\Pachore_Mayuresh_Project_2\Temp\Objects\Config1\X20CP1382\.mappView\0_visulist.json</string><string>D:\Pachore_Mayuresh_ASDP\Pachore_Mayuresh_Project_2\Pachore_Mayuresh_Project_2\Temp\Objects\Config1\X20CP1382\.mappView/data/wwwRoot\0_visulist.json</string><string>D:\Pachore_Mayuresh_ASDP\Pachore_Mayuresh_Project_2\Pachore_Mayuresh_Project_2\Temp\Objects\Config1\X20CP1382\.mappView\Dialog_Sass._markerfile</string><string>D:\Pachore_Mayuresh_ASDP\Pachore_Mayuresh_Project_2\Pachore_Mayuresh_Project_2\Temp\Objects\Config1\X20CP1382\.mappView\Content_Trans._markerfile</string><string>D:\Pachore_Mayuresh_ASDP\Pachore_Mayuresh_Project_2\Pachore_Mayuresh_Project_2\Temp\Objects\Config1\X20CP1382\.mappView\Content_Sass._markerfile</string><string>D:\Pachore_Mayuresh_ASDP\Pachore_Mayuresh_Project_2\Pachore_Mayuresh_Project_2\Temp\Objects\Config1\X20CP1382\.mappView/data/wwwRoot\contents/mappView/ContentTop.html</string><string>D:\Pachore_Mayuresh_ASDP\Pachore_Mayuresh_Project_2\Pachore_Mayuresh_Project_2\Temp\Objects\Config1\X20CP1382\.mappView/data/wwwRoot/BRVisu/css/pages\mappView/ContentTop.scss</string><string>D:\Pachore_Mayuresh_ASDP\Pachore_Mayuresh_Project_2\Pachore_Mayuresh_Project_2\Temp\Objects\Config1\X20CP1382\.mappView/data/wwwRoot/BRVisu/css/pages\mappView/ContentTop.scss.css</string><string>D:\Pachore_Mayuresh_ASDP\Pachore_Mayuresh_Project_2\Pachore_Mayuresh_Project_2\Temp\Objects\Config1\X20CP1382\.mappView/data/wwwRoot\contents/mappView/ContentLeft.html</string><string>D:\Pachore_Mayuresh_ASDP\Pachore_Mayuresh_Project_2\Pachore_Mayuresh_Project_2\Temp\Objects\Config1\X20CP1382\.mappView/data/wwwRoot/BRVisu/css/pages\mappView/ContentLeft.scss</string><string>D:\Pachore_Mayuresh_ASDP\Pachore_Mayuresh_Project_2\Pachore_Mayuresh_Project_2\Temp\Objects\Config1\X20CP1382\.mappView/data/wwwRoot/BRVisu/css/pages\mappView/ContentLeft.scss.css</string><string>D:\Pachore_Mayuresh_ASDP\Pachore_Mayuresh_Project_2\Pachore_Mayuresh_Project_2\Temp\Objects\Config1\X20CP1382\.mappView/data/wwwRoot\contents/mappView/ContentOperate.html</string><string>D:\Pachore_Mayuresh_ASDP\Pachore_Mayuresh_Project_2\Pachore_Mayuresh_Project_2\Temp\Objects\Config1\X20CP1382\.mappView/data/wwwRoot/BRVisu/css/pages\mappView/ContentOperate.scss</string><string>D:\Pachore_Mayuresh_ASDP\Pachore_Mayuresh_Project_2\Pachore_Mayuresh_Project_2\Temp\Objects\Config1\X20CP1382\.mappView/data/wwwRoot/BRVisu/css/pages\mappView/ContentOperate.scss.css</string><string>D:\Pachore_Mayuresh_ASDP\Pachore_Mayuresh_Project_2\Pachore_Mayuresh_Project_2\Temp\Objects\Config1\X20CP1382\.mappView/data/wwwRoot\contents/mappView/ContentManual.html</string><string>D:\Pachore_Mayuresh_ASDP\Pachore_Mayuresh_Project_2\Pachore_Mayuresh_Project_2\Temp\Objects\Config1\X20CP1382\.mappView/data/wwwRoot/BRVisu/css/pages\mappView/ContentManual.scss</string><string>D:\Pachore_Mayuresh_ASDP\Pachore_Mayuresh_Project_2\Pachore_Mayuresh_Project_2\Temp\Objects\Config1\X20CP1382\.mappView/data/wwwRoot/BRVisu/css/pages\mappView/ContentManual.scss.css</string><string>D:\Pachore_Mayuresh_ASDP\Pachore_Mayuresh_Project_2\Pachore_Mayuresh_Project_2\Temp\Objects\Config1\X20CP1382\.mappView/data/wwwRoot\contents/mappView/ContentAdvance.html</string><string>D:\Pachore_Mayuresh_ASDP\Pachore_Mayuresh_Project_2\Pachore_Mayuresh_Project_2\Temp\Objects\Config1\X20CP1382\.mappView/data/wwwRoot/BRVisu/css/pages\mappView/ContentAdvance.scss</string><string>D:\Pachore_Mayuresh_ASDP\Pachore_Mayuresh_Project_2\Pachore_Mayuresh_Project_2\Temp\Objects\Config1\X20CP1382\.mappView/data/wwwRoot/BRVisu/css/pages\mappView/ContentAdvance.scss.css</string><string>D:\Pachore_Mayuresh_ASDP\Pachore_Mayuresh_Project_2\Pachore_Mayuresh_Project_2\Temp\Objects\Config1\X20CP1382\.mappView\data\server\717726808.binding</string><string>D:\Pachore_Mayuresh_ASDP\Pachore_Mayuresh_Project_2\Pachore_Mayuresh_Project_2\Temp\Objects\Config1\X20CP1382\.mappView\data\server\-1436652289.binding</string><string>D:\Pachore_Mayuresh_ASDP\Pachore_Mayuresh_Project_2\Pachore_Mayuresh_Project_2\Temp\Objects\Config1\X20CP1382\.mappView\data\server\-1471344535.binding</string><string>D:\Pachore_Mayuresh_ASDP\Pachore_Mayuresh_Project_2\Pachore_Mayuresh_Project_2\Temp\Objects\Config1\X20CP1382\.mappView/data/server\__SystemVariables.sessionVar</string><string>D:\Pachore_Mayuresh_ASDP\Pachore_Mayuresh_Project_2\Pachore_Mayuresh_Project_2\Temp\Objects\Config1\X20CP1382\.mappView/data/server\Control_Panel.vis</string><string>D:\Pachore_Mayuresh_ASDP\Pachore_Mayuresh_Project_2\Pachore_Mayuresh_Project_2\Temp\Objects\Config1\X20CP1382\.mappView/data/server\Config.mappviewcfg</string></ArrayOfString>